unitpackage/__init__.py
unitpackage/collection.py
unitpackage/descriptor.py
unitpackage/entry.py
unitpackage/entrypoint.py
unitpackage/local.py
unitpackage/remote.py
unitpackage/cv/__init__.py
unitpackage/cv/cv_collection.py
unitpackage/cv/cv_entry.py
unitpackage/database/__init__.py
unitpackage/database/echemdb.py
unitpackage/database/echemdb_entry.py
unitpackage/electrochemistry/__init__.py
unitpackage/electrochemistry/reference_electrode.py
unitpackage/loaders/__init__.py
unitpackage/loaders/baseloader.py
unitpackage/loaders/column_names.py
unitpackage/loaders/eclabloader.py
unitpackage/loaders/gamryloader.py
unitpackage/test/__init__.py
unitpackage/test/cli.py
unitpackage-0.11.2.dist-info/licenses/LICENSE
unitpackage-0.11.2.dist-info/METADATA
unitpackage-0.11.2.dist-info/WHEEL
unitpackage-0.11.2.dist-info/entry_points.txt
unitpackage-0.11.2.dist-info/top_level.txt
unitpackage-0.11.2.dist-info/RECORD
