Metadata-Version: 2.4
Name: unitpackage
Version: 0.11.2
Summary: a Python library to interact with a collection of frictionless datapackages
License-Expression: GPL-3.0-or-later
Requires-Python: >=3.10
License-File: LICENSE
Requires-Dist: astropy<8,>=5
Requires-Dist: click<9,>=8
Requires-Dist: frictionless<6,>=5.8.3
Requires-Dist: matplotlib<4,>=3.5.0
Requires-Dist: pandas<3,>=1.3
Requires-Dist: plotly<7,>=5
Requires-Dist: pybtex<0.26,>=0.25
Dynamic: license-file
